zsv.ticker-1.1.0-py3.8-nspkg.pth
zsv/ticker/__init__.py
zsv/ticker/ticker.py
zsv.ticker-1.1.0.dist-info/LICENSE
zsv.ticker-1.1.0.dist-info/METADATA
zsv.ticker-1.1.0.dist-info/WHEEL
zsv.ticker-1.1.0.dist-info/namespace_packages.txt
zsv.ticker-1.1.0.dist-info/top_level.txt
zsv.ticker-1.1.0.dist-info/RECORD
